{"config":{"output_file":null,"full_docs":false,"pub_only":true,"reachable_only":true,"distro_crate":false,"signatures":false,"borrow_data":false},"prelude":{"crate_id":{"name":"quote","disambiguator":[6853630718863428214,16069372507144512579]},"crate_root":"/home/diegorosario/.cargo/registry/src/github.com-1ecc6299db9ec823/quote-0.4.2/src","external_crates":[{"file_name":"/home/diegorosario/.cargo/registry/src/github.com-1ecc6299db9ec823/quote-0.4.2/src/lib.rs","num":1,"id":{"name":"std","disambiguator":[17753285296391399312,11690687960591772784]}},{"file_name":"/home/diegorosario/.cargo/registry/src/github.com-1ecc6299db9ec823/quote-0.4.2/src/lib.rs","num":2,"id":{"name":"core","disambiguator":[2432787739525035206,9013682043098606205]}},{"file_name":"/home/diegorosario/.cargo/registry/src/github.com-1ecc6299db9ec823/quote-0.4.2/src/lib.rs","num":3,"id":{"name":"compiler_builtins","disambiguator":[15325262305802526375,5466798779206520768]}},{"file_name":"/home/diegorosario/.cargo/registry/src/github.com-1ecc6299db9ec823/quote-0.4.2/src/lib.rs","num":4,"id":{"name":"alloc","disambiguator":[14362642536228645896,10940758137206118220]}},{"file_name":"/home/diegorosario/.cargo/registry/src/github.com-1ecc6299db9ec823/quote-0.4.2/src/lib.rs","num":5,"id":{"name":"alloc_system","disambiguator":[1514312871643377971,12032594248399141928]}},{"file_name":"/home/diegorosario/.cargo/registry/src/github.com-1ecc6299db9ec823/quote-0.4.2/src/lib.rs","num":6,"id":{"name":"libc","disambiguator":[7584708957473716998,8465739101562542308]}},{"file_name":"/home/diegorosario/.cargo/registry/src/github.com-1ecc6299db9ec823/quote-0.4.2/src/lib.rs","num":7,"id":{"name":"unwind","disambiguator":[12895158241221514803,9678506401513259651]}},{"file_name":"/home/diegorosario/.cargo/registry/src/github.com-1ecc6299db9ec823/quote-0.4.2/src/lib.rs","num":8,"id":{"name":"alloc_jemalloc","disambiguator":[9461050523560162386,6982090908028985046]}},{"file_name":"/home/diegorosario/.cargo/registry/src/github.com-1ecc6299db9ec823/quote-0.4.2/src/lib.rs","num":9,"id":{"name":"panic_unwind","disambiguator":[12585024881823035589,8500610919371370866]}},{"file_name":"/home/diegorosario/.cargo/registry/src/github.com-1ecc6299db9ec823/quote-0.4.2/src/lib.rs","num":10,"id":{"name":"proc_macro2","disambiguator":[10721509719038946276,10938331697123836217]}},{"file_name":"/home/diegorosario/.cargo/registry/src/github.com-1ecc6299db9ec823/quote-0.4.2/src/lib.rs","num":11,"id":{"name":"proc_macro","disambiguator":[2868975536760739986,7061119074784189544]}},{"file_name":"/home/diegorosario/.cargo/registry/src/github.com-1ecc6299db9ec823/quote-0.4.2/src/lib.rs","num":12,"id":{"name":"syntax","disambiguator":[9988756131896270443,4286996159916316093]}},{"file_name":"/home/diegorosario/.cargo/registry/src/github.com-1ecc6299db9ec823/quote-0.4.2/src/lib.rs","num":13,"id":{"name":"bitflags","disambiguator":[6973377238138691616,13160866924574990791]}},{"file_name":"/home/diegorosario/.cargo/registry/src/github.com-1ecc6299db9ec823/quote-0.4.2/src/lib.rs","num":14,"id":{"name":"serialize","disambiguator":[8392018146356957909,1079234870507175944]}},{"file_name":"/home/diegorosario/.cargo/registry/src/github.com-1ecc6299db9ec823/quote-0.4.2/src/lib.rs","num":15,"id":{"name":"log","disambiguator":[15696446238576097818,8760571611998136957]}},{"file_name":"/home/diegorosario/.cargo/registry/src/github.com-1ecc6299db9ec823/quote-0.4.2/src/lib.rs","num":16,"id":{"name":"cfg_if","disambiguator":[10907444927126118604,1263099075165525653]}},{"file_name":"/home/diegorosario/.cargo/registry/src/github.com-1ecc6299db9ec823/quote-0.4.2/src/lib.rs","num":17,"id":{"name":"rustc_errors","disambiguator":[2635715450821764621,7544452979036034738]}},{"file_name":"/home/diegorosario/.cargo/registry/src/github.com-1ecc6299db9ec823/quote-0.4.2/src/lib.rs","num":18,"id":{"name":"atty","disambiguator":[6086755992221449424,17317504023736652953]}},{"file_name":"/home/diegorosario/.cargo/registry/src/github.com-1ecc6299db9ec823/quote-0.4.2/src/lib.rs","num":19,"id":{"name":"libc","disambiguator":[3400135157480583001,13735876869595205940]}},{"file_name":"/home/diegorosario/.cargo/registry/src/github.com-1ecc6299db9ec823/quote-0.4.2/src/lib.rs","num":20,"id":{"name":"termcolor","disambiguator":[9389999032748930515,5381001610769401076]}},{"file_name":"/home/diegorosario/.cargo/registry/src/github.com-1ecc6299db9ec823/quote-0.4.2/src/lib.rs","num":21,"id":{"name":"rustc_data_structures","disambiguator":[1697789455833954792,7630599643012772864]}},{"file_name":"/home/diegorosario/.cargo/registry/src/github.com-1ecc6299db9ec823/quote-0.4.2/src/lib.rs","num":22,"id":{"name":"ena","disambiguator":[8800429476315708892,17100695709607692836]}},{"file_name":"/home/diegorosario/.cargo/registry/src/github.com-1ecc6299db9ec823/quote-0.4.2/src/lib.rs","num":23,"id":{"name":"parking_lot","disambiguator":[17025015524909010682,13176822267113475910]}},{"file_name":"/home/diegorosario/.cargo/registry/src/github.com-1ecc6299db9ec823/quote-0.4.2/src/lib.rs","num":24,"id":{"name":"owning_ref","disambiguator":[17467425740141378124,10662833808889097151]}},{"file_name":"/home/diegorosario/.cargo/registry/src/github.com-1ecc6299db9ec823/quote-0.4.2/src/lib.rs","num":25,"id":{"name":"stable_deref_trait","disambiguator":[11450681007700942271,10822399968832365881]}},{"file_name":"/home/diegorosario/.cargo/registry/src/github.com-1ecc6299db9ec823/quote-0.4.2/src/lib.rs","num":26,"id":{"name":"parking_lot_core","disambiguator":[8445697879365577539,16479192281026612843]}},{"file_name":"/home/diegorosario/.cargo/registry/src/github.com-1ecc6299db9ec823/quote-0.4.2/src/lib.rs","num":27,"id":{"name":"rand","disambiguator":[4692476821411905501,12744995134518629650]}},{"file_name":"/home/diegorosario/.cargo/registry/src/github.com-1ecc6299db9ec823/quote-0.4.2/src/lib.rs","num":28,"id":{"name":"smallvec","disambiguator":[11380896984559498743,8377714361132138026]}},{"file_name":"/home/diegorosario/.cargo/registry/src/github.com-1ecc6299db9ec823/quote-0.4.2/src/lib.rs","num":29,"id":{"name":"rustc_rayon","disambiguator":[15720553395863082007,5619795728580792738]}},{"file_name":"/home/diegorosario/.cargo/registry/src/github.com-1ecc6299db9ec823/quote-0.4.2/src/lib.rs","num":30,"id":{"name":"rustc_rayon_core","disambiguator":[6831476326565880169,4153534759893917734]}},{"file_name":"/home/diegorosario/.cargo/registry/src/github.com-1ecc6299db9ec823/quote-0.4.2/src/lib.rs","num":31,"id":{"name":"crossbeam_deque","disambiguator":[1702335555245687243,7801501012903939811]}},{"file_name":"/home/diegorosario/.cargo/registry/src/github.com-1ecc6299db9ec823/quote-0.4.2/src/lib.rs","num":32,"id":{"name":"crossbeam_epoch","disambiguator":[10095561300326699171,243001456433720536]}},{"file_name":"/home/diegorosario/.cargo/registry/src/github.com-1ecc6299db9ec823/quote-0.4.2/src/lib.rs","num":33,"id":{"name":"nodrop","disambiguator":[8474076257858879423,7822977366802464890]}},{"file_name":"/home/diegorosario/.cargo/registry/src/github.com-1ecc6299db9ec823/quote-0.4.2/src/lib.rs","num":34,"id":{"name":"arrayvec","disambiguator":[10206133767018440629,8611030712820177349]}},{"file_name":"/home/diegorosario/.cargo/registry/src/github.com-1ecc6299db9ec823/quote-0.4.2/src/lib.rs","num":35,"id":{"name":"crossbeam_utils","disambiguator":[13608154028096106365,4136097443023158370]}},{"file_name":"/home/diegorosario/.cargo/registry/src/github.com-1ecc6299db9ec823/quote-0.4.2/src/lib.rs","num":36,"id":{"name":"lazy_static","disambiguator":[451369850417848321,7081224173623912481]}},{"file_name":"/home/diegorosario/.cargo/registry/src/github.com-1ecc6299db9ec823/quote-0.4.2/src/lib.rs","num":37,"id":{"name":"memoffset","disambiguator":[13030093493657398200,16765634726977947502]}},{"file_name":"/home/diegorosario/.cargo/registry/src/github.com-1ecc6299db9ec823/quote-0.4.2/src/lib.rs","num":38,"id":{"name":"scopeguard","disambiguator":[16257516784138767249,4717722680927176697]}},{"file_name":"/home/diegorosario/.cargo/registry/src/github.com-1ecc6299db9ec823/quote-0.4.2/src/lib.rs","num":39,"id":{"name":"num_cpus","disambiguator":[7703296793916474944,16683801078449602750]}},{"file_name":"/home/diegorosario/.cargo/registry/src/github.com-1ecc6299db9ec823/quote-0.4.2/src/lib.rs","num":40,"id":{"name":"either","disambiguator":[1446353310584428807,18293344890516300738]}},{"file_name":"/home/diegorosario/.cargo/registry/src/github.com-1ecc6299db9ec823/quote-0.4.2/src/lib.rs","num":41,"id":{"name":"rustc_hash","disambiguator":[8130361520457875489,18118050890324457962]}},{"file_name":"/home/diegorosario/.cargo/registry/src/github.com-1ecc6299db9ec823/quote-0.4.2/src/lib.rs","num":42,"id":{"name":"byteorder","disambiguator":[8946004220023339082,6847702305083435923]}},{"file_name":"/home/diegorosario/.cargo/registry/src/github.com-1ecc6299db9ec823/quote-0.4.2/src/lib.rs","num":43,"id":{"name":"rustc_cratesio_shim","disambiguator":[2015791253015479238,8107494325334788195]}},{"file_name":"/home/diegorosario/.cargo/registry/src/github.com-1ecc6299db9ec823/quote-0.4.2/src/lib.rs","num":44,"id":{"name":"syntax_pos","disambiguator":[1635817934917308179,15812435185738614072]}},{"file_name":"/home/diegorosario/.cargo/registry/src/github.com-1ecc6299db9ec823/quote-0.4.2/src/lib.rs","num":45,"id":{"name":"arena","disambiguator":[3606248012687745789,2400280005472855693]}},{"file_name":"/home/diegorosario/.cargo/registry/src/github.com-1ecc6299db9ec823/quote-0.4.2/src/lib.rs","num":46,"id":{"name":"scoped_tls","disambiguator":[398293545616501204,7353333805941732772]}},{"file_name":"/home/diegorosario/.cargo/registry/src/github.com-1ecc6299db9ec823/quote-0.4.2/src/lib.rs","num":47,"id":{"name":"unicode_width","disambiguator":[12079719933181405099,2336254388723023739]}},{"file_name":"/home/diegorosario/.cargo/registry/src/github.com-1ecc6299db9ec823/quote-0.4.2/src/lib.rs","num":48,"id":{"name":"rustc_target","disambiguator":[14073851611273674864,18122815630301737689]}},{"file_name":"/home/diegorosario/.cargo/registry/src/github.com-1ecc6299db9ec823/quote-0.4.2/src/lib.rs","num":49,"id":{"name":"unicode_xid","disambiguator":[16526312224248629949,6787527203701567819]}}],"span":{"file_name":[47,104,111,109,101,47,100,105,101,103,111,114,111,115,97,114,105,111,47,46,99,97,114,103,111,47,114,101,103,105,115,116,114,121,47,115,114,99,47,103,105,116,104,117,98,46,99,111,109,45,49,101,99,99,54,50,57,57,100,98,57,101,99,56,50,51,47,113,117,111,116,101,45,48,46,52,46,50,47,115,114,99,47,108,105,98,46,114,115],"byte_start":0,"byte_end":15830,"line_start":1,"line_end":501,"column_start":1,"column_end":2}},"imports":[{"kind":"Use","ref_id":{"krate":0,"index":234},"span":{"file_name":[47,104,111,109,101,47,100,105,101,103,111,114,111,115,97,114,105,111,47,46,99,97,114,103,111,47,114,101,103,105,115,116,114,121,47,115,114,99,47,103,105,116,104,117,98,46,99,111,109,45,49,101,99,99,54,50,57,57,100,98,57,101,99,56,50,51,47,113,117,111,116,101,45,48,46,52,46,50,47,115,114,99,47,108,105,98,46,114,115],"byte_start":3446,"byte_end":3452,"line_start":100,"line_end":100,"column_start":17,"column_end":23},"alias_span":null,"name":"Tokens","value":"","parent":{"krate":0,"index":0}},{"kind":"Use","ref_id":{"krate":0,"index":152},"span":{"file_name":[47,104,111,109,101,47,100,105,101,103,111,114,111,115,97,114,105,111,47,46,99,97,114,103,111,47,114,101,103,105,115,116,114,121,47,115,114,99,47,103,105,116,104,117,98,46,99,111,109,45,49,101,99,99,54,50,57,57,100,98,57,101,99,56,50,51,47,113,117,111,116,101,45,48,46,52,46,50,47,115,114,99,47,108,105,98,46,114,115],"byte_start":3489,"byte_end":3497,"line_start":103,"line_end":103,"column_start":20,"column_end":28},"alias_span":null,"name":"ToTokens","value":"","parent":{"krate":0,"index":0}},{"kind":"GlobUse","ref_id":null,"span":{"file_name":[47,104,111,109,101,47,100,105,101,103,111,114,111,115,97,114,105,111,47,46,99,97,114,103,111,47,114,101,103,105,115,116,114,121,47,115,114,99,47,103,105,116,104,117,98,46,99,111,109,45,49,101,99,99,54,50,57,57,100,98,57,101,99,56,50,51,47,113,117,111,116,101,45,48,46,52,46,50,47,115,114,99,47,108,105,98,46,114,115],"byte_start":3597,"byte_end":3598,"line_start":109,"line_end":109,"column_start":26,"column_end":27},"alias_span":null,"name":"*","value":"TokenNode, TokenStream, Span, TokenTree","parent":{"krate":0,"index":214}}],"defs":[{"kind":"Mod","id":{"krate":0,"index":0},"span":{"file_name":[47,104,111,109,101,47,100,105,101,103,111,114,111,115,97,114,105,111,47,46,99,97,114,103,111,47,114,101,103,105,115,116,114,121,47,115,114,99,47,103,105,116,104,117,98,46,99,111,109,45,49,101,99,99,54,50,57,57,100,98,57,101,99,56,50,51,47,113,117,111,116,101,45,48,46,52,46,50,47,115,114,99,47,108,105,98,46,114,115],"byte_start":0,"byte_end":15830,"line_start":1,"line_end":501,"column_start":1,"column_end":2},"name":"","qualname":"::","value":"/home/diegorosario/.cargo/registry/src/github.com-1ecc6299db9ec823/quote-0.4.2/src/lib.rs","parent":null,"children":[{"krate":0,"index":2},{"krate":0,"index":4},{"krate":0,"index":6},{"krate":0,"index":8},{"krate":0,"index":10},{"krate":0,"index":128},{"krate":0,"index":130},{"krate":0,"index":212},{"krate":0,"index":214},{"krate":0,"index":222},{"krate":0,"index":224},{"krate":0,"index":226},{"krate":0,"index":228},{"krate":0,"index":230},{"krate":0,"index":232}],"decl_id":null,"docs":" This crate provides the [`quote!`] macro for turning Rust syntax tree data\n structures into tokens of source code.","sig":null,"attributes":[]},{"kind":"Struct","id":{"krate":0,"index":234},"span":{"file_name":[47,104,111,109,101,47,100,105,101,103,111,114,111,115,97,114,105,111,47,46,99,97,114,103,111,47,114,101,103,105,115,116,114,121,47,115,114,99,47,103,105,116,104,117,98,46,99,111,109,45,49,101,99,99,54,50,57,57,100,98,57,101,99,56,50,51,47,113,117,111,116,101,45,48,46,52,46,50,47,115,114,99,47,116,111,107,101,110,115,46,114,115],"byte_start":16105,"byte_end":16111,"line_start":12,"line_end":12,"column_start":12,"column_end":18},"name":"Tokens","qualname":"::tokens::Tokens","value":"Tokens {  }","parent":null,"children":[{"krate":0,"index":75}],"decl_id":null,"docs":" Tokens produced by a [`quote!`] invocation.","sig":null,"attributes":[]},{"kind":"Method","id":{"krate":0,"index":38},"span":{"file_name":[47,104,111,109,101,47,100,105,101,103,111,114,111,115,97,114,105,111,47,46,99,97,114,103,111,47,114,101,103,105,115,116,114,121,47,115,114,99,47,103,105,116,104,117,98,46,99,111,109,45,49,101,99,99,54,50,57,57,100,98,57,101,99,56,50,51,47,113,117,111,116,101,45,48,46,52,46,50,47,115,114,99,47,116,111,107,101,110,115,46,114,115],"byte_start":16189,"byte_end":16192,"line_start":18,"line_end":18,"column_start":12,"column_end":15},"name":"new","qualname":"<Tokens>::new","value":"fn () -> Self","parent":null,"children":[],"decl_id":null,"docs":" Empty tokens.\n","sig":null,"attributes":[]},{"kind":"Method","id":{"krate":0,"index":40},"span":{"file_name":[47,104,111,109,101,47,100,105,101,103,111,114,111,115,97,114,105,111,47,46,99,97,114,103,111,47,114,101,103,105,115,116,114,121,47,115,114,99,47,103,105,116,104,117,98,46,99,111,109,45,49,101,99,99,54,50,57,57,100,98,57,101,99,56,50,51,47,113,117,111,116,101,45,48,46,52,46,50,47,115,114,99,47,116,111,107,101,110,115,46,114,115],"byte_start":16373,"byte_end":16379,"line_start":25,"line_end":25,"column_start":12,"column_end":18},"name":"append","qualname":"<Tokens>::append","value":"fn <U> (&mut self, token: U) -> ()","parent":null,"children":[],"decl_id":null,"docs":" For use by `ToTokens` implementations.","sig":null,"attributes":[]},{"kind":"Method","id":{"krate":0,"index":42},"span":{"file_name":[47,104,111,109,101,47,100,105,101,103,111,114,111,115,97,114,105,111,47,46,99,97,114,103,111,47,114,101,103,105,115,116,114,121,47,115,114,99,47,103,105,116,104,117,98,46,99,111,109,45,49,101,99,99,54,50,57,57,100,98,57,101,99,56,50,51,47,113,117,111,116,101,45,48,46,52,46,50,47,115,114,99,47,116,111,107,101,110,115,46,114,115],"byte_start":16981,"byte_end":16991,"line_start":50,"line_end":50,"column_start":12,"column_end":22},"name":"append_all","qualname":"<Tokens>::append_all","value":"fn <T, I> (&mut self, iter: I) -> ()","parent":null,"children":[],"decl_id":null,"docs":" For use by `ToTokens` implementations.","sig":null,"attributes":[]},{"kind":"Method","id":{"krate":0,"index":44},"span":{"file_name":[47,104,111,109,101,47,100,105,101,103,111,114,111,115,97,114,105,111,47,46,99,97,114,103,111,47,114,101,103,105,115,116,114,121,47,115,114,99,47,103,105,116,104,117,98,46,99,111,109,45,49,101,99,99,54,50,57,57,100,98,57,101,99,56,50,51,47,113,117,111,116,101,45,48,46,52,46,50,47,115,114,99,47,116,111,107,101,110,115,46,114,115],"byte_start":17327,"byte_end":17343,"line_start":64,"line_end":64,"column_start":12,"column_end":28},"name":"append_separated","qualname":"<Tokens>::append_separated","value":"fn <T, I, U> (&mut self, iter: I, op: U) -> ()","parent":null,"children":[],"decl_id":null,"docs":" For use by `ToTokens` implementations.","sig":null,"attributes":[]},{"kind":"Method","id":{"krate":0,"index":46},"span":{"file_name":[47,104,111,109,101,47,100,105,101,103,111,114,111,115,97,114,105,111,47,46,99,97,114,103,111,47,114,101,103,105,115,116,114,121,47,115,114,99,47,103,105,116,104,117,98,46,99,111,109,45,49,101,99,99,54,50,57,57,100,98,57,101,99,56,50,51,47,113,117,111,116,101,45,48,46,52,46,50,47,115,114,99,47,116,111,107,101,110,115,46,114,115],"byte_start":17861,"byte_end":17878,"line_start":82,"line_end":82,"column_start":12,"column_end":29},"name":"append_terminated","qualname":"<Tokens>::append_terminated","value":"fn <T, I, U> (&mut self, iter: I, term: U) -> ()","parent":null,"children":[],"decl_id":null,"docs":" For use by `ToTokens` implementations.","sig":null,"attributes":[]},{"kind":"Struct","id":{"krate":0,"index":76},"span":{"file_name":[47,104,111,109,101,47,100,105,101,103,111,114,111,115,97,114,105,111,47,46,99,97,114,103,111,47,114,101,103,105,115,116,114,121,47,115,114,99,47,103,105,116,104,117,98,46,99,111,109,45,49,101,99,99,54,50,57,57,100,98,57,101,99,56,50,51,47,113,117,111,116,101,45,48,46,52,46,50,47,115,114,99,47,116,111,107,101,110,115,46,114,115],"byte_start":18938,"byte_end":18946,"line_start":131,"line_end":131,"column_start":16,"column_end":24},"name":"IntoIter","qualname":"::tokens::private::IntoIter","value":"","parent":null,"children":[],"decl_id":null,"docs":"","sig":null,"attributes":[]},{"kind":"Trait","id":{"krate":0,"index":152},"span":{"file_name":[47,104,111,109,101,47,100,105,101,103,111,114,111,115,97,114,105,111,47,46,99,97,114,103,111,47,114,101,103,105,115,116,114,121,47,115,114,99,47,103,105,116,104,117,98,46,99,111,109,45,49,101,99,99,54,50,57,57,100,98,57,101,99,56,50,51,47,113,117,111,116,101,45,48,46,52,46,50,47,115,114,99,47,116,111,95,116,111,107,101,110,115,46,114,115],"byte_start":23161,"byte_end":23169,"line_start":17,"line_end":17,"column_start":11,"column_end":19},"name":"ToTokens","qualname":"::to_tokens::ToTokens","value":"ToTokens","parent":null,"children":[{"krate":0,"index":154},{"krate":0,"index":156}],"decl_id":null,"docs":" Types that can be interpolated inside a [`quote!`] invocation.","sig":null,"attributes":[]},{"kind":"Method","id":{"krate":0,"index":154},"span":{"file_name":[47,104,111,109,101,47,100,105,101,103,111,114,111,115,97,114,105,111,47,46,99,97,114,103,111,47,114,101,103,105,115,116,114,121,47,115,114,99,47,103,105,116,104,117,98,46,99,111,109,45,49,101,99,99,54,50,57,57,100,98,57,101,99,56,50,51,47,113,117,111,116,101,45,48,46,52,46,50,47,115,114,99,47,116,111,95,116,111,107,101,110,115,46,114,115],"byte_start":24676,"byte_end":24685,"line_start":64,"line_end":64,"column_start":8,"column_end":17},"name":"to_tokens","qualname":"::to_tokens::ToTokens::to_tokens","value":"fn (&self, tokens: &mut Tokens) -> ()","parent":{"krate":0,"index":152},"children":[],"decl_id":null,"docs":" Write `self` to the given `Tokens`.","sig":null,"attributes":[]},{"kind":"Method","id":{"krate":0,"index":156},"span":{"file_name":[47,104,111,109,101,47,100,105,101,103,111,114,111,115,97,114,105,111,47,46,99,97,114,103,111,47,114,101,103,105,115,116,114,121,47,115,114,99,47,103,105,116,104,117,98,46,99,111,109,45,49,101,99,99,54,50,57,57,100,98,57,101,99,56,50,51,47,113,117,111,116,101,45,48,46,52,46,50,47,115,114,99,47,116,111,95,116,111,107,101,110,115,46,114,115],"byte_start":24932,"byte_end":24943,"line_start":70,"line_end":70,"column_start":8,"column_end":19},"name":"into_tokens","qualname":"::to_tokens::ToTokens::into_tokens","value":"fn (self) -> Tokens","parent":{"krate":0,"index":152},"children":[],"decl_id":null,"docs":" Convert `self` directly into a `Tokens` object.","sig":null,"attributes":[]},{"kind":"Mod","id":{"krate":0,"index":214},"span":{"file_name":[47,104,111,109,101,47,100,105,101,103,111,114,111,115,97,114,105,111,47,46,99,97,114,103,111,47,114,101,103,105,115,116,114,121,47,115,114,99,47,103,105,116,104,117,98,46,99,111,109,45,49,101,99,99,54,50,57,57,100,98,57,101,99,56,50,51,47,113,117,111,116,101,45,48,46,52,46,50,47,115,114,99,47,108,105,98,46,114,115],"byte_start":3542,"byte_end":3546,"line_start":107,"line_end":107,"column_start":9,"column_end":13},"name":"__rt","qualname":"::__rt","value":"/home/diegorosario/.cargo/registry/src/github.com-1ecc6299db9ec823/quote-0.4.2/src/lib.rs","parent":null,"children":[{"krate":0,"index":216},{"krate":0,"index":218},{"krate":0,"index":220}],"decl_id":null,"docs":"","sig":null,"attributes":[]},{"kind":"Function","id":{"krate":0,"index":218},"span":{"file_name":[47,104,111,109,101,47,100,105,101,103,111,114,111,115,97,114,105,111,47,46,99,97,114,103,111,47,114,101,103,105,115,116,114,121,47,115,114,99,47,103,105,116,104,117,98,46,99,111,109,45,49,101,99,99,54,50,57,57,100,98,57,101,99,56,50,51,47,113,117,111,116,101,45,48,46,52,46,50,47,115,114,99,47,108,105,98,46,114,115],"byte_start":3635,"byte_end":3640,"line_start":112,"line_end":112,"column_start":12,"column_end":17},"name":"parse","qualname":"::__rt::parse","value":"fn (tokens: &mut ::Tokens, span: Span, s: &str) -> ()","parent":null,"children":[],"decl_id":null,"docs":"","sig":null,"attributes":[]},{"kind":"Function","id":{"krate":0,"index":220},"span":{"file_name":[47,104,111,109,101,47,100,105,101,103,111,114,111,115,97,114,105,111,47,46,99,97,114,103,111,47,114,101,103,105,115,116,114,121,47,115,114,99,47,103,105,116,104,117,98,46,99,111,109,45,49,101,99,99,54,50,57,57,100,98,57,101,99,56,50,51,47,113,117,111,116,101,45,48,46,52,46,50,47,115,114,99,47,108,105,98,46,114,115],"byte_start":3907,"byte_end":3918,"line_start":121,"line_end":121,"column_start":12,"column_end":23},"name":"append_kind","qualname":"::__rt::append_kind","value":"fn (tokens: &mut ::Tokens, span: Span, kind: TokenNode) -> ()","parent":null,"children":[],"decl_id":null,"docs":"","sig":null,"attributes":[]}],"impls":[{"id":0,"kind":"Inherent","span":{"file_name":[47,104,111,109,101,47,100,105,101,103,111,114,111,115,97,114,105,111,47,46,99,97,114,103,111,47,114,101,103,105,115,116,114,121,47,115,114,99,47,103,105,116,104,117,98,46,99,111,109,45,49,101,99,99,54,50,57,57,100,98,57,101,99,56,50,51,47,113,117,111,116,101,45,48,46,52,46,50,47,115,114,99,47,116,111,107,101,110,115,46,114,115],"byte_start":16147,"byte_end":16153,"line_start":16,"line_end":16,"column_start":6,"column_end":12},"value":"","parent":null,"children":[{"krate":0,"index":38},{"krate":0,"index":40},{"krate":0,"index":42},{"krate":0,"index":44},{"krate":0,"index":46}],"docs":"","sig":null,"attributes":[]},{"id":1,"kind":"Direct","span":{"file_name":[47,104,111,109,101,47,100,105,101,103,111,114,111,115,97,114,105,111,47,46,99,97,114,103,111,47,114,101,103,105,115,116,114,121,47,115,114,99,47,103,105,116,104,117,98,46,99,111,109,45,49,101,99,99,54,50,57,57,100,98,57,101,99,56,50,51,47,113,117,111,116,101,45,48,46,52,46,50,47,115,114,99,47,116,111,107,101,110,115,46,114,115],"byte_start":18144,"byte_end":18150,"line_start":95,"line_end":95,"column_start":19,"column_end":25},"value":"","parent":null,"children":[{"krate":0,"index":50},{"krate":0,"index":52}],"docs":"","sig":null,"attributes":[]},{"id":2,"kind":"Direct","span":{"file_name":[47,104,111,109,101,47,100,105,101,103,111,114,111,115,97,114,105,111,47,46,99,97,114,103,111,47,114,101,103,105,115,116,114,121,47,115,114,99,47,103,105,116,104,117,98,46,99,111,109,45,49,101,99,99,54,50,57,57,100,98,57,101,99,56,50,51,47,113,117,111,116,101,45,48,46,52,46,50,47,115,114,99,47,116,111,107,101,110,115,46,114,115],"byte_start":18335,"byte_end":18346,"line_start":105,"line_end":105,"column_start":23,"column_end":34},"value":"","parent":null,"children":[{"krate":0,"index":56}],"docs":"","sig":null,"attributes":[]},{"id":3,"kind":"Direct","span":{"file_name":[47,104,111,109,101,47,100,105,101,103,111,114,111,115,97,114,105,111,47,46,99,97,114,103,111,47,114,101,103,105,115,116,114,121,47,115,114,99,47,103,105,116,104,117,98,46,99,111,109,45,49,101,99,99,54,50,57,57,100,98,57,101,99,56,50,51,47,113,117,111,116,101,45,48,46,52,46,50,47,115,114,99,47,116,111,107,101,110,115,46,114,115],"byte_start":18478,"byte_end":18489,"line_start":111,"line_end":111,"column_start":35,"column_end":46},"value":"","parent":null,"children":[{"krate":0,"index":60}],"docs":"","sig":null,"attributes":[]},{"id":4,"kind":"Direct","span":{"file_name":[47,104,111,109,101,47,100,105,101,103,111,114,111,115,97,114,105,111,47,46,99,97,114,103,111,47,114,101,103,105,115,116,114,121,47,115,114,99,47,103,105,116,104,117,98,46,99,111,109,45,49,101,99,99,54,50,57,57,100,98,57,101,99,56,50,51,47,113,117,111,116,101,45,48,46,52,46,50,47,115,114,99,47,116,111,107,101,110,115,46,114,115],"byte_start":18681,"byte_end":18687,"line_start":118,"line_end":118,"column_start":23,"column_end":29},"value":"","parent":null,"children":[{"krate":0,"index":64},{"krate":0,"index":66},{"krate":0,"index":68}],"docs":"","sig":null,"attributes":[]},{"id":5,"kind":"Direct","span":{"file_name":[47,104,111,109,101,47,100,105,101,103,111,114,111,115,97,114,105,111,47,46,99,97,114,103,111,47,114,101,103,105,115,116,114,121,47,115,114,99,47,103,105,116,104,117,98,46,99,111,109,45,49,101,99,99,54,50,57,57,100,98,57,101,99,56,50,51,47,113,117,111,116,101,45,48,46,52,46,50,47,115,114,99,47,116,111,107,101,110,115,46,114,115],"byte_start":19092,"byte_end":19100,"line_start":137,"line_end":137,"column_start":23,"column_end":31},"value":"","parent":null,"children":[{"krate":0,"index":82},{"krate":0,"index":84}],"docs":"","sig":null,"attributes":[]},{"id":6,"kind":"Direct","span":{"file_name":[47,104,111,109,101,47,100,105,101,103,111,114,111,115,97,114,105,111,47,46,99,97,114,103,111,47,114,101,103,105,115,116,114,121,47,115,114,99,47,103,105,116,104,117,98,46,99,111,109,45,49,101,99,99,54,50,57,57,100,98,57,101,99,56,50,51,47,113,117,111,116,101,45,48,46,52,46,50,47,115,114,99,47,116,111,107,101,110,115,46,114,115],"byte_start":19248,"byte_end":19254,"line_start":146,"line_end":146,"column_start":18,"column_end":24},"value":"","parent":null,"children":[{"krate":0,"index":88}],"docs":"","sig":null,"attributes":[]},{"id":7,"kind":"Direct","span":{"file_name":[47,104,111,109,101,47,100,105,101,103,111,114,111,115,97,114,105,111,47,46,99,97,114,103,111,47,114,101,103,105,115,116,114,121,47,115,114,99,47,103,105,116,104,117,98,46,99,111,109,45,49,101,99,99,54,50,57,57,100,98,57,101,99,56,50,51,47,113,117,111,116,101,45,48,46,52,46,50,47,115,114,99,47,116,111,107,101,110,115,46,114,115],"byte_start":19414,"byte_end":19420,"line_start":152,"line_end":152,"column_start":16,"column_end":22},"value":"","parent":null,"children":[{"krate":0,"index":92}],"docs":"","sig":null,"attributes":[]},{"id":8,"kind":"Direct","span":{"file_name":[47,104,111,109,101,47,100,105,101,103,111,114,111,115,97,114,105,111,47,46,99,97,114,103,111,47,114,101,103,105,115,116,114,121,47,115,114,99,47,103,105,116,104,117,98,46,99,111,109,45,49,101,99,99,54,50,57,57,100,98,57,101,99,56,50,51,47,113,117,111,116,101,45,48,46,52,46,50,47,115,114,99,47,116,111,107,101,110,115,46,114,115],"byte_start":19570,"byte_end":19584,"line_start":156,"line_end":156,"column_start":31,"column_end":45},"value":"","parent":null,"children":[{"krate":0,"index":98}],"docs":"","sig":null,"attributes":[]},{"id":9,"kind":"Direct","span":{"file_name":[47,104,111,109,101,47,100,105,101,103,111,114,111,115,97,114,105,111,47,46,99,97,114,103,111,47,114,101,103,105,115,116,114,121,47,115,114,99,47,103,105,116,104,117,98,46,99,111,109,45,49,101,99,99,54,50,57,57,100,98,57,101,99,56,50,51,47,113,117,111,116,101,45,48,46,52,46,50,47,115,114,99,47,116,111,107,101,110,115,46,114,115],"byte_start":21381,"byte_end":21387,"line_start":213,"line_end":213,"column_start":20,"column_end":26},"value":"","parent":null,"children":[{"krate":0,"index":112}],"docs":"","sig":null,"attributes":[]},{"id":10,"kind":"Direct","span":{"file_name":[47,104,111,109,101,47,100,105,101,103,111,114,111,115,97,114,105,111,47,46,99,97,114,103,111,47,114,101,103,105,115,116,114,121,47,115,114,99,47,103,105,116,104,117,98,46,99,111,109,45,49,101,99,99,54,50,57,57,100,98,57,101,99,56,50,51,47,113,117,111,116,101,45,48,46,52,46,50,47,115,114,99,47,116,111,107,101,110,115,46,114,115],"byte_start":22651,"byte_end":22657,"line_start":257,"line_end":257,"column_start":19,"column_end":25},"value":"","parent":null,"children":[{"krate":0,"index":126}],"docs":"","sig":null,"attributes":[]},{"id":11,"kind":"Direct","span":{"file_name":[47,104,111,109,101,47,100,105,101,103,111,114,111,115,97,114,105,111,47,46,99,97,114,103,111,47,114,101,103,105,115,116,114,121,47,115,114,99,47,103,105,116,104,117,98,46,99,111,109,45,49,101,99,99,54,50,57,57,100,98,57,101,99,56,50,51,47,113,117,111,116,101,45,48,46,52,46,50,47,115,114,99,47,116,111,95,116,111,107,101,110,115,46,114,115],"byte_start":25296,"byte_end":25299,"line_start":86,"line_end":86,"column_start":55,"column_end":58},"value":"","parent":null,"children":[{"krate":0,"index":164}],"docs":"","sig":null,"attributes":[]},{"id":12,"kind":"Direct","span":{"file_name":[47,104,111,109,101,47,100,105,101,103,111,114,111,115,97,114,105,111,47,46,99,97,114,103,111,47,114,101,103,105,115,116,114,121,47,115,114,99,47,103,105,116,104,117,98,46,99,111,109,45,49,101,99,99,54,50,57,57,100,98,57,101,99,56,50,51,47,113,117,111,116,101,45,48,46,52,46,50,47,115,114,99,47,116,111,95,116,111,107,101,110,115,46,114,115],"byte_start":25441,"byte_end":25444,"line_start":92,"line_end":92,"column_start":41,"column_end":44},"value":"","parent":null,"children":[{"krate":0,"index":168}],"docs":"","sig":null,"attributes":[]},{"id":13,"kind":"Direct","span":{"file_name":[47,104,111,109,101,47,100,105,101,103,111,114,111,115,97,114,105,111,47,46,99,97,114,103,111,47,114,101,103,105,115,116,114,121,47,115,114,99,47,103,105,116,104,117,98,46,99,111,109,45,49,101,99,99,54,50,57,57,100,98,57,101,99,56,50,51,47,113,117,111,116,101,45,48,46,52,46,50,47,115,114,99,47,116,111,95,116,111,107,101,110,115,46,114,115],"byte_start":25573,"byte_end":25579,"line_start":98,"line_end":98,"column_start":32,"column_end":38},"value":"","parent":null,"children":[{"krate":0,"index":172}],"docs":"","sig":null,"attributes":[]},{"id":15,"kind":"Direct","span":{"file_name":[47,104,111,109,101,47,100,105,101,103,111,114,111,115,97,114,105,111,47,46,99,97,114,103,111,47,114,101,103,105,115,116,114,121,47,115,114,99,47,103,105,116,104,117,98,46,99,111,109,45,49,101,99,99,54,50,57,57,100,98,57,101,99,56,50,51,47,113,117,111,116,101,45,48,46,52,46,50,47,115,114,99,47,116,111,95,116,111,107,101,110,115,46,114,115],"byte_start":25889,"byte_end":25895,"line_start":112,"line_end":112,"column_start":19,"column_end":25},"value":"","parent":null,"children":[{"krate":0,"index":180}],"docs":"","sig":null,"attributes":[]},{"id":18,"kind":"Direct","span":{"file_name":[47,104,111,109,101,47,100,105,101,103,111,114,111,115,97,114,105,111,47,46,99,97,114,103,111,47,114,101,103,105,115,116,114,121,47,115,114,99,47,103,105,116,104,117,98,46,99,111,109,45,49,101,99,99,54,50,57,57,100,98,57,101,99,56,50,51,47,113,117,111,116,101,45,48,46,52,46,50,47,115,114,99,47,116,111,95,116,111,107,101,110,115,46,114,115],"byte_start":26695,"byte_end":26699,"line_start":147,"line_end":147,"column_start":19,"column_end":23},"value":"","parent":null,"children":[{"krate":0,"index":194}],"docs":"","sig":null,"attributes":[]},{"id":19,"kind":"Direct","span":{"file_name":[47,104,111,109,101,47,100,105,101,103,111,114,111,115,97,114,105,111,47,46,99,97,114,103,111,47,114,101,103,105,115,116,114,121,47,115,114,99,47,103,105,116,104,117,98,46,99,111,109,45,49,101,99,99,54,50,57,57,100,98,57,101,99,56,50,51,47,113,117,111,116,101,45,48,46,52,46,50,47,115,114,99,47,116,111,95,116,111,107,101,110,115,46,114,115],"byte_start":26827,"byte_end":26834,"line_start":153,"line_end":153,"column_start":19,"column_end":26},"value":"","parent":null,"children":[{"krate":0,"index":198}],"docs":"","sig":null,"attributes":[]},{"id":20,"kind":"Direct","span":{"file_name":[47,104,111,109,101,47,100,105,101,103,111,114,111,115,97,114,105,111,47,46,99,97,114,103,111,47,114,101,103,105,115,116,114,121,47,115,114,99,47,103,105,116,104,117,98,46,99,111,109,45,49,101,99,99,54,50,57,57,100,98,57,101,99,56,50,51,47,113,117,111,116,101,45,48,46,52,46,50,47,115,114,99,47,116,111,95,116,111,107,101,110,115,46,114,115],"byte_start":26972,"byte_end":26981,"line_start":159,"line_end":159,"column_start":19,"column_end":28},"value":"","parent":null,"children":[{"krate":0,"index":202}],"docs":"","sig":null,"attributes":[]},{"id":21,"kind":"Direct","span":{"file_name":[47,104,111,109,101,47,100,105,101,103,111,114,111,115,97,114,105,111,47,46,99,97,114,103,111,47,114,101,103,105,115,116,114,121,47,115,114,99,47,103,105,116,104,117,98,46,99,111,109,45,49,101,99,99,54,50,57,57,100,98,57,101,99,56,50,51,47,113,117,111,116,101,45,48,46,52,46,50,47,115,114,99,47,116,111,95,116,111,107,101,110,115,46,114,115],"byte_start":27099,"byte_end":27108,"line_start":165,"line_end":165,"column_start":19,"column_end":28},"value":"","parent":null,"children":[{"krate":0,"index":206}],"docs":"","sig":null,"attributes":[]},{"id":22,"kind":"Direct","span":{"file_name":[47,104,111,109,101,47,100,105,101,103,111,114,111,115,97,114,105,111,47,46,99,97,114,103,111,47,114,101,103,105,115,116,114,121,47,115,114,99,47,103,105,116,104,117,98,46,99,111,109,45,49,101,99,99,54,50,57,57,100,98,57,101,99,56,50,51,47,113,117,111,116,101,45,48,46,52,46,50,47,115,114,99,47,116,111,95,116,111,107,101,110,115,46,114,115],"byte_start":27216,"byte_end":27227,"line_start":171,"line_end":171,"column_start":19,"column_end":30},"value":"","parent":null,"children":[{"krate":0,"index":210}],"docs":"","sig":null,"attributes":[]}],"refs":[],"macro_refs":[],"relations":[{"span":{"file_name":[47,104,111,109,101,47,100,105,101,103,111,114,111,115,97,114,105,111,47,46,99,97,114,103,111,47,114,101,103,105,115,116,114,121,47,115,114,99,47,103,105,116,104,117,98,46,99,111,109,45,49,101,99,99,54,50,57,57,100,98,57,101,99,56,50,51,47,113,117,111,116,101,45,48,46,52,46,50,47,115,114,99,47,116,111,107,101,110,115,46,114,115],"byte_start":16147,"byte_end":16153,"line_start":16,"line_end":16,"column_start":6,"column_end":12},"kind":{"variant":"Impl","fields":[0]},"from":{"krate":0,"index":234},"to":{"krate":4294967295,"index":4294967295}},{"span":{"file_name":[47,104,111,109,101,47,100,105,101,103,111,114,111,115,97,114,105,111,47,46,99,97,114,103,111,47,114,101,103,105,115,116,114,121,47,115,114,99,47,103,105,116,104,117,98,46,99,111,109,45,49,101,99,99,54,50,57,57,100,98,57,101,99,56,50,51,47,113,117,111,116,101,45,48,46,52,46,50,47,115,114,99,47,116,111,107,101,110,115,46,114,115],"byte_start":18144,"byte_end":18150,"line_start":95,"line_end":95,"column_start":19,"column_end":25},"kind":{"variant":"Impl","fields":[1]},"from":{"krate":0,"index":234},"to":{"krate":0,"index":152}},{"span":{"file_name":[47,104,111,109,101,47,100,105,101,103,111,114,111,115,97,114,105,111,47,46,99,97,114,103,111,47,114,101,103,105,115,116,114,121,47,115,114,99,47,103,105,116,104,117,98,46,99,111,109,45,49,101,99,99,54,50,57,57,100,98,57,101,99,56,50,51,47,113,117,111,116,101,45,48,46,52,46,50,47,115,114,99,47,116,111,107,101,110,115,46,114,115],"byte_start":18335,"byte_end":18346,"line_start":105,"line_end":105,"column_start":23,"column_end":34},"kind":{"variant":"Impl","fields":[2]},"from":{"krate":10,"index":548},"to":{"krate":2,"index":2676}},{"span":{"file_name":[47,104,111,109,101,47,100,105,101,103,111,114,111,115,97,114,105,111,47,46,99,97,114,103,111,47,114,101,103,105,115,116,114,121,47,115,114,99,47,103,105,116,104,117,98,46,99,111,109,45,49,101,99,99,54,50,57,57,100,98,57,101,99,56,50,51,47,113,117,111,116,101,45,48,46,52,46,50,47,115,114,99,47,116,111,107,101,110,115,46,114,115],"byte_start":18478,"byte_end":18489,"line_start":111,"line_end":111,"column_start":35,"column_end":46},"kind":{"variant":"Impl","fields":[3]},"from":{"krate":11,"index":616},"to":{"krate":2,"index":2676}},{"span":{"file_name":[47,104,111,109,101,47,100,105,101,103,111,114,111,115,97,114,105,111,47,46,99,97,114,103,111,47,114,101,103,105,115,116,114,121,47,115,114,99,47,103,105,116,104,117,98,46,99,111,109,45,49,101,99,99,54,50,57,57,100,98,57,101,99,56,50,51,47,113,117,111,116,101,45,48,46,52,46,50,47,115,114,99,47,116,111,107,101,110,115,46,114,115],"byte_start":18681,"byte_end":18687,"line_start":118,"line_end":118,"column_start":23,"column_end":29},"kind":{"variant":"Impl","fields":[4]},"from":{"krate":0,"index":234},"to":{"krate":2,"index":4252}},{"span":{"file_name":[47,104,111,109,101,47,100,105,101,103,111,114,111,115,97,114,105,111,47,46,99,97,114,103,111,47,114,101,103,105,115,116,114,121,47,115,114,99,47,103,105,116,104,117,98,46,99,111,109,45,49,101,99,99,54,50,57,57,100,98,57,101,99,56,50,51,47,113,117,111,116,101,45,48,46,52,46,50,47,115,114,99,47,116,111,107,101,110,115,46,114,115],"byte_start":19092,"byte_end":19100,"line_start":137,"line_end":137,"column_start":23,"column_end":31},"kind":{"variant":"Impl","fields":[5]},"from":{"krate":0,"index":76},"to":{"krate":2,"index":3892}},{"span":{"file_name":[47,104,111,109,101,47,100,105,101,103,111,114,111,115,97,114,105,111,47,46,99,97,114,103,111,47,114,101,103,105,115,116,114,121,47,115,114,99,47,103,105,116,104,117,98,46,99,111,109,45,49,101,99,99,54,50,57,57,100,98,57,101,99,56,50,51,47,113,117,111,116,101,45,48,46,52,46,50,47,115,114,99,47,116,111,107,101,110,115,46,114,115],"byte_start":19248,"byte_end":19254,"line_start":146,"line_end":146,"column_start":18,"column_end":24},"kind":{"variant":"Impl","fields":[6]},"from":{"krate":0,"index":234},"to":{"krate":2,"index":7860}},{"span":{"file_name":[47,104,111,109,101,47,100,105,101,103,111,114,111,115,97,114,105,111,47,46,99,97,114,103,111,47,114,101,103,105,115,116,114,121,47,115,114,99,47,103,105,116,104,117,98,46,99,111,109,45,49,101,99,99,54,50,57,57,100,98,57,101,99,56,50,51,47,113,117,111,116,101,45,48,46,52,46,50,47,115,114,99,47,116,111,107,101,110,115,46,114,115],"byte_start":19414,"byte_end":19420,"line_start":152,"line_end":152,"column_start":16,"column_end":22},"kind":{"variant":"Impl","fields":[7]},"from":{"krate":0,"index":234},"to":{"krate":2,"index":7856}},{"span":{"file_name":[47,104,111,109,101,47,100,105,101,103,111,114,111,115,97,114,105,111,47,46,99,97,114,103,111,47,114,101,103,105,115,116,114,121,47,115,114,99,47,103,105,116,104,117,98,46,99,111,109,45,49,101,99,99,54,50,57,57,100,98,57,101,99,56,50,51,47,113,117,111,116,101,45,48,46,52,46,50,47,115,114,99,47,116,111,107,101,110,115,46,114,115],"byte_start":19570,"byte_end":19584,"line_start":156,"line_end":156,"column_start":31,"column_end":45},"kind":{"variant":"Impl","fields":[8]},"from":{"krate":0,"index":94},"to":{"krate":2,"index":7856}},{"span":{"file_name":[47,104,111,109,101,47,100,105,101,103,111,114,111,115,97,114,105,111,47,46,99,97,114,103,111,47,114,101,103,105,115,116,114,121,47,115,114,99,47,103,105,116,104,117,98,46,99,111,109,45,49,101,99,99,54,50,57,57,100,98,57,101,99,56,50,51,47,113,117,111,116,101,45,48,46,52,46,50,47,115,114,99,47,116,111,107,101,110,115,46,114,115],"byte_start":21381,"byte_end":21387,"line_start":213,"line_end":213,"column_start":20,"column_end":26},"kind":{"variant":"Impl","fields":[9]},"from":{"krate":0,"index":234},"to":{"krate":2,"index":2434}},{"span":{"file_name":[47,104,111,109,101,47,100,105,101,103,111,114,111,115,97,114,105,111,47,46,99,97,114,103,111,47,114,101,103,105,115,116,114,121,47,115,114,99,47,103,105,116,104,117,98,46,99,111,109,45,49,101,99,99,54,50,57,57,100,98,57,101,99,56,50,51,47,113,117,111,116,101,45,48,46,52,46,50,47,115,114,99,47,116,111,107,101,110,115,46,114,115],"byte_start":22651,"byte_end":22657,"line_start":257,"line_end":257,"column_start":19,"column_end":25},"kind":{"variant":"Impl","fields":[10]},"from":{"krate":0,"index":234},"to":{"krate":2,"index":7428}},{"span":{"file_name":[47,104,111,109,101,47,100,105,101,103,111,114,111,115,97,114,105,111,47,46,99,97,114,103,111,47,114,101,103,105,115,116,114,121,47,115,114,99,47,103,105,116,104,117,98,46,99,111,109,45,49,101,99,99,54,50,57,57,100,98,57,101,99,56,50,51,47,113,117,111,116,101,45,48,46,52,46,50,47,115,114,99,47,116,111,95,116,111,107,101,110,115,46,114,115],"byte_start":25296,"byte_end":25299,"line_start":86,"line_end":86,"column_start":55,"column_end":58},"kind":{"variant":"Impl","fields":[11]},"from":{"krate":4,"index":3462},"to":{"krate":0,"index":152}},{"span":{"file_name":[47,104,111,109,101,47,100,105,101,103,111,114,111,115,97,114,105,111,47,46,99,97,114,103,111,47,114,101,103,105,115,116,114,121,47,115,114,99,47,103,105,116,104,117,98,46,99,111,109,45,49,101,99,99,54,50,57,57,100,98,57,101,99,56,50,51,47,113,117,111,116,101,45,48,46,52,46,50,47,115,114,99,47,116,111,95,116,111,107,101,110,115,46,114,115],"byte_start":25441,"byte_end":25444,"line_start":92,"line_end":92,"column_start":41,"column_end":44},"kind":{"variant":"Impl","fields":[12]},"from":{"krate":4,"index":192},"to":{"krate":0,"index":152}},{"span":{"file_name":[47,104,111,109,101,47,100,105,101,103,111,114,111,115,97,114,105,111,47,46,99,97,114,103,111,47,114,101,103,105,115,116,114,121,47,115,114,99,47,103,105,116,104,117,98,46,99,111,109,45,49,101,99,99,54,50,57,57,100,98,57,101,99,56,50,51,47,113,117,111,116,101,45,48,46,52,46,50,47,115,114,99,47,116,111,95,116,111,107,101,110,115,46,114,115],"byte_start":25573,"byte_end":25579,"line_start":98,"line_end":98,"column_start":32,"column_end":38},"kind":{"variant":"Impl","fields":[13]},"from":{"krate":2,"index":41364},"to":{"krate":0,"index":152}},{"span":{"file_name":[47,104,111,109,101,47,100,105,101,103,111,114,111,115,97,114,105,111,47,46,99,97,114,103,111,47,114,101,103,105,115,116,114,121,47,115,114,99,47,103,105,116,104,117,98,46,99,111,109,45,49,101,99,99,54,50,57,57,100,98,57,101,99,56,50,51,47,113,117,111,116,101,45,48,46,52,46,50,47,115,114,99,47,116,111,95,116,111,107,101,110,115,46,114,115],"byte_start":25889,"byte_end":25895,"line_start":112,"line_end":112,"column_start":19,"column_end":25},"kind":{"variant":"Impl","fields":[15]},"from":{"krate":4,"index":5494},"to":{"krate":0,"index":152}},{"span":{"file_name":[47,104,111,109,101,47,100,105,101,103,111,114,111,115,97,114,105,111,47,46,99,97,114,103,111,47,114,101,103,105,115,116,114,121,47,115,114,99,47,103,105,116,104,117,98,46,99,111,109,45,49,101,99,99,54,50,57,57,100,98,57,101,99,56,50,51,47,113,117,111,116,101,45,48,46,52,46,50,47,115,114,99,47,116,111,95,116,111,107,101,110,115,46,114,115],"byte_start":26695,"byte_end":26699,"line_start":147,"line_end":147,"column_start":19,"column_end":23},"kind":{"variant":"Impl","fields":[18]},"from":{"krate":10,"index":602},"to":{"krate":0,"index":152}},{"span":{"file_name":[47,104,111,109,101,47,100,105,101,103,111,114,111,115,97,114,105,111,47,46,99,97,114,103,111,47,114,101,103,105,115,116,114,121,47,115,114,99,47,103,105,116,104,117,98,46,99,111,109,45,49,101,99,99,54,50,57,57,100,98,57,101,99,56,50,51,47,113,117,111,116,101,45,48,46,52,46,50,47,115,114,99,47,116,111,95,116,111,107,101,110,115,46,114,115],"byte_start":26827,"byte_end":26834,"line_start":153,"line_end":153,"column_start":19,"column_end":26},"kind":{"variant":"Impl","fields":[19]},"from":{"krate":10,"index":630},"to":{"krate":0,"index":152}},{"span":{"file_name":[47,104,111,109,101,47,100,105,101,103,111,114,111,115,97,114,105,111,47,46,99,97,114,103,111,47,114,101,103,105,115,116,114,121,47,115,114,99,47,103,105,116,104,117,98,46,99,111,109,45,49,101,99,99,54,50,57,57,100,98,57,101,99,56,50,51,47,113,117,111,116,101,45,48,46,52,46,50,47,115,114,99,47,116,111,95,116,111,107,101,110,115,46,114,115],"byte_start":26972,"byte_end":26981,"line_start":159,"line_end":159,"column_start":19,"column_end":28},"kind":{"variant":"Impl","fields":[20]},"from":{"krate":10,"index":572},"to":{"krate":0,"index":152}},{"span":{"file_name":[47,104,111,109,101,47,100,105,101,103,111,114,111,115,97,114,105,111,47,46,99,97,114,103,111,47,114,101,103,105,115,116,114,121,47,115,114,99,47,103,105,116,104,117,98,46,99,111,109,45,49,101,99,99,54,50,57,57,100,98,57,101,99,56,50,51,47,113,117,111,116,101,45,48,46,52,46,50,47,115,114,99,47,116,111,95,116,111,107,101,110,115,46,114,115],"byte_start":27099,"byte_end":27108,"line_start":165,"line_end":165,"column_start":19,"column_end":28},"kind":{"variant":"Impl","fields":[21]},"from":{"krate":10,"index":562},"to":{"krate":0,"index":152}},{"span":{"file_name":[47,104,111,109,101,47,100,105,101,103,111,114,111,115,97,114,105,111,47,46,99,97,114,103,111,47,114,101,103,105,115,116,114,121,47,115,114,99,47,103,105,116,104,117,98,46,99,111,109,45,49,101,99,99,54,50,57,57,100,98,57,101,99,56,50,51,47,113,117,111,116,101,45,48,46,52,46,50,47,115,114,99,47,116,111,95,116,111,107,101,110,115,46,114,115],"byte_start":27216,"byte_end":27227,"line_start":171,"line_end":171,"column_start":19,"column_end":30},"kind":{"variant":"Impl","fields":[22]},"from":{"krate":10,"index":548},"to":{"krate":0,"index":152}}]}